LICENSE
MANIFEST.in
setup.py
utox/__init__.py
utox/_version.py
utox/annotationutil.py
utox/fileutil.py
utox/iniutil.py
utox/log.py
utox/timeutil.py
utox/util.py
utox.egg-info/PKG-INFO
utox.egg-info/SOURCES.txt
utox.egg-info/dependency_links.txt
utox.egg-info/not-zip-safe
utox.egg-info/top_level.txt