Metadata-Version: 2.1
Name: utox
Version: 0.0.7
Summary: my utils
Home-page: https://github.com/bme6/utox
Author: ly
Author-email: 2662017230@qq.com
Classifier: Programming Language :: Python :: 3
Classifier: Operating System :: OS Independent
Classifier: License :: OSI Approved :: Apache Software License
Requires-Python: >=3.8
License-File: LICENSE
